{"AF_left": {"svr": "9.412241365489406", "xgb": "5.9693904", "stack_reg_1": "9.032329"}, "AF_right": {"svr": "5.494250229019591", "xgb": "7.8438215", "stack_reg_1": "7.4302945"}, "CC_1": {"svr": "6.962323807925879", "xgb": "6.752623", "stack_reg_1": "9.186353"}, "CC_2": {"svr": "6.504249629562759", "xgb": "5.5857654", "stack_reg_1": "10.268231"}, "CC_3": {"svr": "6.683187523503466", "xgb": "6.6131606", "stack_reg_1": "8.483453"}, "CC_4": {"svr": "5.04770121806882", "xgb": "5.8178144", "stack_reg_1": "5.312685"}, "CC_5": {"svr": "6.894879274140718", "xgb": "7.9477925", "stack_reg_1": "6.0578403"}, "CC_6": {"svr": "5.142499665041078", "xgb": "3.505478", "stack_reg_1": "5.9816747"}, "CC_7": {"svr": "5.979053285766496", "xgb": "6.240794", "stack_reg_1": "11.017374"}, "CG_left": {"svr": "5.433650274399021", "xgb": "6.706146", "stack_reg_1": "9.936085"}, "CG_right": {"svr": "3.698100062107861", "xgb": "4.9023542", "stack_reg_1": "8.591171"}, "CST_left": {"svr": "5.429033806037285", "xgb": "5.8682995", "stack_reg_1": "5.314598"}, "CST_right": {"svr": "2.467215770816439", "xgb": "7.539143", "stack_reg_1": "8.60003"}, "FX_left": {"svr": "8.37511174562326", "xgb": "10.3913145", "stack_reg_1": "15.653155"}, "FX_right": {"svr": "8.835931533233406", "xgb": "11.368036", "stack_reg_1": "13.146527"}, "IFO_left": {"svr": "7.049770352624545", "xgb": "7.3586497", "stack_reg_1": "9.267472"}, "IFO_right": {"svr": "7.886453997189007", "xgb": "9.359679", "stack_reg_1": "6.6710267"}, "ILF_left": {"svr": "8.764705153607373", "xgb": "8.500448", "stack_reg_1": "12.601737"}, "ILF_right": {"svr": "6.148205172365558", "xgb": "9.345905", "stack_reg_1": "9.064551"}, "SLF_III_left": {"svr": "7.7856418097695945", "xgb": "11.104636", "stack_reg_1": "8.218552"}, "SLF_III_right": {"svr": "5.331003772178085", "xgb": "4.6383333", "stack_reg_1": "9.456605"}, "SLF_II_left": {"svr": "3.657539390029108", "xgb": "5.8908095", "stack_reg_1": "5.1437607"}, "SLF_II_right": {"svr": "4.09753669245433", "xgb": "4.6820745", "stack_reg_1": "6.889331"}, "SLF_I_left": {"svr": "3.40463275284778", "xgb": "6.3134933", "stack_reg_1": "12.705909"}, "SLF_I_right": {"svr": "4.718531476160728", "xgb": "5.778003", "stack_reg_1": "6.421596"}, "T_PREF_left": {"svr": "3.1606519368625396", "xgb": "4.7213073", "stack_reg_1": "5.322135"}, "T_PREF_right": {"svr": "4.468158809281807", "xgb": "4.5232754", "stack_reg_1": "7.766658"}, "UF_left": {"svr": "4.759888483783476", "xgb": "5.1926007", "stack_reg_1": "8.442254"}, "UF_right": {"svr": "4.922939949168401", "xgb": "8.515808", "stack_reg_1": "7.72168"}, "val_averaged_all_svr": "3.496302093565622", "val_averaged_top3_svr": "2.4171675570602535", "test_averaged_all_svr": "6.197395148247257", "test_averaged_top3_svr": "7.105149039133248", "top_features_svr": ["T_PREF_left", "CST_right", "SLF_I_left"], "val_averaged_all_xgb": "4.259768", "val_averaged_top3_xgb": "3.020035", "test_averaged_all_xgb": "6.6597824", "test_averaged_top3_xgb": "5.765829", "top_features_xgb": ["T_PREF_right", "CC_6", "SLF_III_right"], "val_averaged_all_stack_reg_1": "5.9082975", "val_averaged_top3_stack_reg_1": "3.8767145", "test_averaged_all_stack_reg_1": "8.029669", "test_averaged_top3_stack_reg_1": "8.575124", "top_features_stack_reg_1": ["SLF_II_left", "CC_4", "CST_left"], "val_averaged_top3_ensemble": "2.480049907201918"}